dag_insight_plugin/__init__.py
dag_insight_plugin/my_plugins/__init__.py
dag_insight_plugin/my_plugins/dag_insight.py
dag_insight_plugin/my_plugins/helper/event_driven_dags_query.sql
dag_insight_plugin/my_plugins/templates/dag_insight.html
dag_insight_plugin-0.1.0a2.dist-info/LICENSE
dag_insight_plugin-0.1.0a2.dist-info/METADATA
dag_insight_plugin-0.1.0a2.dist-info/NOTICE
dag_insight_plugin-0.1.0a2.dist-info/WHEEL
dag_insight_plugin-0.1.0a2.dist-info/entry_points.txt
dag_insight_plugin-0.1.0a2.dist-info/RECORD
