Metadata-Version: 2.1
Name: dag-insight-plugin
Version: 0.1.0a2
Summary: An Apache Airflow plugin that visualizes DAG runs in a Gantt chart, predicts future runs, and identifies tasks that won't execute. Enhance your workflow monitoring and planning with intuitive visualizations.
License: MIT
Author: Hipposys
Requires-Python: >=3.10,<4.0
Classifier: License :: OSI Approved :: MIT License
Classifier: Programming Language :: Python :: 3
Classifier: Programming Language :: Python :: 3.10
Classifier: Programming Language :: Python :: 3.11
Classifier: Programming Language :: Python :: 3.12
Classifier: Programming Language :: Python :: 3.13
Requires-Dist: SQLAlchemy (>=1.4.0)
Requires-Dist: apache-airflow (>=2.4.0,<3.0.0)
Requires-Dist: pandas (>=1.3.5)
Project-URL: homepage, https://github.com/hipposys-ltd/airflow-dag-insight
